nouns/__init__.py
nouns/builtin_templates/default.html
nouns/builtin_templates/iterable.html
nouns/builtin_templates/mapping.html
nouns/builtin_templates/mappingrow.html
nouns/builtin_templates/number.html
nouns/builtin_templates/table.html
nouns/builtin_templates/tablecell.html
nouns/builtin_templates/tableheading.html
nouns/builtin_templates/tablerow.html
nouns/builtin_templates/text.html
nouns/builtin_templates/thingy.html
nouns/css/__init__.py
nouns/obj/__init__.py
nouns/obj/human.py
nouns/obj/xobject.py
nouns/templates/__init__.py
nouns-0.1.1.dist-info/entry_points.txt
nouns-0.1.1.dist-info/LICENSE
nouns-0.1.1.dist-info/WHEEL
nouns-0.1.1.dist-info/METADATA
nouns-0.1.1.dist-info/RECORD
