Metadata-Version: 2.1
Name: nouns
Version: 0.1.1
Summary: Data-driven templating
Author: Robert Lechte
Author-email: robert.lechte@dpc.vic.gov.au
Requires-Python: >=3.8
Classifier: Programming Language :: Python :: 3
Classifier: Programming Language :: Python :: 3.8
Requires-Dist: results
